safeparser
