Metadata-Version: 2.1
Name: safe-parser
Version: 0.1.3
Summary: A simple parser of python-line code that can be safely executed
Home-page: https://github.com/jdferreira/safe-parser
Author: João D. Ferreira
Author-email: jotomicron@gmail.com
License: UNKNOWN
Platform: UNKNOWN
Classifier: Programming Language :: Python :: 3
Classifier: License :: OSI Approved :: MIT License
Classifier: Operating System :: OS Independent
